{
	"editor": {
		"allAngles": false,
		"entityTextureMode": false
	},
	"textureWidth": 16,
	"textureHeight": 16,
	"textureSizes": {
	},
	"textures": {
		"redpaintedsteelwrench": "item/redpaintedsteelwrench",
		"bluepaintedwornsteelplate": "block/metal/bluepaintedwornsteelplate",
		"wornsteel": "block/metal/wornsteel"
	},
	"elements": [
		{
			"name": "motorcore",
			"from": [ 0.0, 0.0, 4.0 ], 
			"to": [ 8.0, 8.0, 11.0 ], 
			"rotationOrigin": [ 0.0, 0.0, 4.0 ],
			"faces": {
				"north": { "texture": "#wornsteel", "uv": [ 7.5, 0.0, 15.5, 8.0 ] },
				"east": { "texture": "#wornsteel", "uv": [ 0.0, 0.0, 7.0, 8.0 ] },
				"south": { "texture": "#wornsteel", "uv": [ 0.0, 0.0, 8.0, 8.0 ], "enabled": false },
				"west": { "texture": "#wornsteel", "uv": [ 0.0, 0.0, 7.0, 8.0 ] },
				"up": { "texture": "#wornsteel", "uv": [ 2.5, 7.5, 10.5, 14.5 ] },
				"down": { "texture": "#wornsteel", "uv": [ 0.0, 0.0, 8.0, 7.0 ] }
			},
			"children": [
				{
					"name": "Cube3",
					"from": [ 1.0, 0.0, -1.0 ], 
					"to": [ 7.0, 8.0, 0.0 ], 
					"rotationOrigin": [ 1.0, 0.0, -1.0 ],
					"faces": {
						"north": { "texture": "#wornsteel", "uv": [ 0.0, 0.0, 6.0, 8.0 ] },
						"east": { "texture": "#wornsteel", "uv": [ 0.0, 0.0, 1.0, 8.0 ] },
						"south": { "texture": "#wornsteel", "uv": [ 0.0, 0.0, 6.0, 8.0 ], "enabled": false },
						"west": { "texture": "#wornsteel", "uv": [ 0.0, 0.0, 1.0, 8.0 ] },
						"up": { "texture": "#wornsteel", "uv": [ 0.0, 0.0, 6.0, 1.0 ] },
						"down": { "texture": "#wornsteel", "uv": [ 0.0, 0.0, 6.0, 1.0 ] }
					}
				},
				{
					"name": "motorcoreedgetrim",
					"from": [ 0.0, 0.0, 7.0 ], 
					"to": [ 1.0, 8.0, 8.0 ], 
					"rotationOrigin": [ 0.0, 0.0, 7.0 ],
					"faces": {
						"north": { "texture": "#wornsteel", "uv": [ 7.5, 0.0, 8.5, 8.0 ], "enabled": false },
						"east": { "texture": "#wornsteel", "uv": [ 0.0, 0.0, 1.0, 8.0 ] },
						"south": { "texture": "#wornsteel", "uv": [ 0.0, 0.0, 1.0, 8.0 ] },
						"west": { "texture": "#wornsteel", "uv": [ 2.0, 1.5, 3.0, 9.5 ] },
						"up": { "texture": "#wornsteel", "uv": [ 7.0, 2.0, 8.0, 3.0 ] },
						"down": { "texture": "#wornsteel", "uv": [ 0.0, 0.0, 1.0, 1.0 ] }
					}
				},
				{
					"name": "motorcoreedgetrim14",
					"from": [ 7.0, 0.0, 7.0 ], 
					"to": [ 8.0, 8.0, 8.0 ], 
					"rotationOrigin": [ 7.0, 0.0, 7.0 ],
					"faces": {
						"north": { "texture": "#wornsteel", "uv": [ 7.5, 0.0, 8.5, 8.0 ], "enabled": false },
						"east": { "texture": "#wornsteel", "uv": [ 0.0, 0.0, 1.0, 8.0 ] },
						"south": { "texture": "#wornsteel", "uv": [ 0.0, 0.0, 1.0, 8.0 ] },
						"west": { "texture": "#wornsteel", "uv": [ 0.0, 0.0, 1.0, 8.0 ], "enabled": false },
						"up": { "texture": "#wornsteel", "uv": [ 10.0, 7.0, 11.0, 8.0 ] },
						"down": { "texture": "#wornsteel", "uv": [ 0.0, 0.0, 1.0, 1.0 ] }
					}
				},
				{
					"name": "motorcoreedgetrim15",
					"from": [ 1.0, 0.0, 7.0 ], 
					"to": [ 7.0, 1.0, 8.0 ], 
					"rotationOrigin": [ 1.0, 0.0, 7.0 ],
					"faces": {
						"north": { "texture": "#wornsteel", "uv": [ 7.5, 0.0, 13.5, 1.0 ], "enabled": false },
						"east": { "texture": "#wornsteel", "uv": [ 0.0, 0.0, 1.0, 1.0 ], "enabled": false },
						"south": { "texture": "#wornsteel", "uv": [ 0.0, 0.0, 6.0, 1.0 ] },
						"west": { "texture": "#wornsteel", "uv": [ 0.0, 0.0, 1.0, 1.0 ], "enabled": false },
						"up": { "texture": "#wornsteel", "uv": [ 2.5, 7.5, 8.5, 8.5 ], "enabled": false },
						"down": { "texture": "#wornsteel", "uv": [ 0.0, 0.0, 6.0, 1.0 ] }
					}
				},
				{
					"name": "ventinterior",
					"from": [ 1.0, 7.0, 7.0 ], 
					"to": [ 7.0, 8.0, 8.0 ], 
					"rotationOrigin": [ 1.0, 7.0, 7.0 ],
					"faces": {
						"north": { "texture": "#wornsteel", "uv": [ 7.5, 0.0, 13.5, 1.0 ], "enabled": false },
						"east": { "texture": "#wornsteel", "uv": [ 0.0, 0.0, 1.0, 1.0 ], "enabled": false },
						"south": { "texture": "#wornsteel", "uv": [ 0.0, 0.0, 6.0, 1.0 ], "enabled": false },
						"west": { "texture": "#wornsteel", "uv": [ 0.0, 0.0, 1.0, 1.0 ], "enabled": false },
						"up": { "texture": "#wornsteel", "uv": [ 5.5, 11.0, 11.5, 12.0 ] },
						"down": { "texture": "#wornsteel", "uv": [ 0.0, 0.0, 6.0, 1.0 ], "enabled": false }
					}
				},
				{
					"name": "behindvent",
					"from": [ 1.0, 1.0, 7.0 ], 
					"to": [ 7.0, 7.0, 8.0 ], 
					"rotationOrigin": [ 1.0, 1.0, 7.0 ],
					"faces": {
						"north": { "texture": "#wornsteel", "uv": [ 7.5, 0.0, 13.5, 6.0 ], "enabled": false },
						"east": { "texture": "#wornsteel", "uv": [ 0.0, 0.0, 1.0, 6.0 ], "enabled": false },
						"south": { "texture": "#redpaintedsteelwrench", "uv": [ 7.0, 1.0, 10.0, 7.0 ], "autoUv": false },
						"west": { "texture": "#wornsteel", "uv": [ 0.0, 0.0, 1.0, 6.0 ], "enabled": false },
						"up": { "texture": "#wornsteel", "uv": [ 2.5, 7.5, 8.5, 8.5 ], "enabled": false },
						"down": { "texture": "#redpaintedsteelwrench", "uv": [ 0.0, 0.0, 6.0, 1.0 ], "enabled": false }
					}
				}
			]
		},
		{
			"name": "Red Vent",
			"from": [ 1.0, 1.0, 12.0 ], 
			"to": [ 2.0, 7.0, 13.0 ], 
			"rotationOrigin": [ 1.0, 1.0, 12.0 ],
			"faces": {
				"north": { "texture": "#redpaintedsteelwrench", "uv": [ 0.0, 0.0, 1.0, 6.0 ], "enabled": false },
				"east": { "texture": "#redpaintedsteelwrench", "uv": [ 9.0, 9.0, 10.0, 15.0 ] },
				"south": { "texture": "#redpaintedsteelwrench", "uv": [ 5.5, 9.5, 6.5, 15.5 ] },
				"west": { "texture": "#redpaintedsteelwrench", "uv": [ 6.5, 9.0, 7.5, 15.0 ] },
				"up": { "texture": "#redpaintedsteelwrench", "uv": [ 0.0, 0.0, 1.0, 1.0 ], "enabled": false },
				"down": { "texture": "#redpaintedsteelwrench", "uv": [ 0.0, 0.0, 1.0, 1.0 ], "enabled": false }
			},
			"children": [
				{
					"name": "VentVane12",
					"from": [ 1.0, 5.0, 0.0 ], 
					"to": [ 5.0, 5.5, 0.5 ], 
					"rotationOrigin": [ 1.0, 5.0, 0.0 ],
					"faces": {
						"north": { "texture": "#redpaintedsteelwrench", "uv": [ 0.0, 0.0, 4.0, 0.5 ], "enabled": false },
						"east": { "texture": "#redpaintedsteelwrench", "uv": [ 0.0, 0.0, 0.5, 0.5 ], "enabled": false },
						"south": { "texture": "#redpaintedsteelwrench", "uv": [ 1.5, 13.0, 5.5, 13.5 ] },
						"west": { "texture": "#redpaintedsteelwrench", "uv": [ 0.0, 0.0, 0.5, 0.5 ], "enabled": false },
						"up": { "texture": "#redpaintedsteelwrench", "uv": [ 6.5, 12.5, 10.5, 13.0 ] },
						"down": { "texture": "#redpaintedsteelwrench", "uv": [ 6.5, 11.5, 10.5, 12.0 ] }
					}
				},
				{
					"name": "VentVane11",
					"from": [ 1.0, 4.0, 0.0 ], 
					"to": [ 5.0, 4.5, 0.5 ], 
					"rotationOrigin": [ 1.0, 4.0, 0.0 ],
					"faces": {
						"north": { "texture": "#redpaintedsteelwrench", "uv": [ 0.0, 0.0, 4.0, 0.5 ], "enabled": false },
						"east": { "texture": "#redpaintedsteelwrench", "uv": [ 0.0, 0.0, 0.5, 0.5 ], "enabled": false },
						"south": { "texture": "#redpaintedsteelwrench", "uv": [ 7.0, 12.5, 11.0, 13.0 ] },
						"west": { "texture": "#redpaintedsteelwrench", "uv": [ 0.0, 0.0, 0.5, 0.5 ], "enabled": false },
						"up": { "texture": "#redpaintedsteelwrench", "uv": [ 6.5, 11.0, 10.5, 11.5 ] },
						"down": { "texture": "#redpaintedsteelwrench", "uv": [ 6.5, 10.5, 10.5, 11.0 ] }
					}
				},
				{
					"name": "VentVane10",
					"from": [ 1.0, 3.0, 0.0 ], 
					"to": [ 5.0, 3.5, 0.5 ], 
					"rotationOrigin": [ 1.0, 3.0, 0.0 ],
					"faces": {
						"north": { "texture": "#redpaintedsteelwrench", "uv": [ 0.0, 0.0, 4.0, 0.5 ], "enabled": false },
						"east": { "texture": "#redpaintedsteelwrench", "uv": [ 0.0, 0.0, 0.5, 0.5 ], "enabled": false },
						"south": { "texture": "#redpaintedsteelwrench", "uv": [ 1.5, 13.5, 5.5, 14.0 ] },
						"west": { "texture": "#redpaintedsteelwrench", "uv": [ 0.0, 0.0, 0.5, 0.5 ], "enabled": false },
						"up": { "texture": "#redpaintedsteelwrench", "uv": [ 2.0, 13.0, 6.0, 13.5 ] },
						"down": { "texture": "#redpaintedsteelwrench", "uv": [ 1.5, 13.0, 5.5, 13.5 ] }
					}
				},
				{
					"name": "VentVane9",
					"from": [ 1.0, 2.0, 0.0 ], 
					"to": [ 5.0, 2.5, 0.5 ], 
					"rotationOrigin": [ 1.0, 2.0, 0.0 ],
					"faces": {
						"north": { "texture": "#redpaintedsteelwrench", "uv": [ 0.0, 0.0, 4.0, 0.5 ], "enabled": false },
						"east": { "texture": "#redpaintedsteelwrench", "uv": [ 0.0, 0.0, 0.5, 0.5 ], "enabled": false },
						"south": { "texture": "#redpaintedsteelwrench", "uv": [ 5.5, 14.0, 9.5, 14.5 ] },
						"west": { "texture": "#redpaintedsteelwrench", "uv": [ 0.0, 0.0, 0.5, 0.5 ], "enabled": false },
						"up": { "texture": "#redpaintedsteelwrench", "uv": [ 5.5, 13.0, 9.5, 13.5 ] },
						"down": { "texture": "#redpaintedsteelwrench", "uv": [ 5.5, 13.5, 9.5, 14.0 ] }
					}
				},
				{
					"name": "VentVane8",
					"from": [ 1.0, 1.0, 0.0 ], 
					"to": [ 5.0, 1.5, 0.5 ], 
					"rotationOrigin": [ 1.0, 1.0, 0.0 ],
					"faces": {
						"north": { "texture": "#redpaintedsteelwrench", "uv": [ 0.0, 0.0, 4.0, 0.5 ], "enabled": false },
						"east": { "texture": "#redpaintedsteelwrench", "uv": [ 0.0, 0.0, 0.5, 0.5 ], "enabled": false },
						"south": { "texture": "#redpaintedsteelwrench", "uv": [ 6.5, 13.0, 10.5, 13.5 ] },
						"west": { "texture": "#redpaintedsteelwrench", "uv": [ 0.0, 0.0, 0.5, 0.5 ], "enabled": false },
						"up": { "texture": "#redpaintedsteelwrench", "uv": [ 6.5, 13.0, 10.5, 13.5 ] },
						"down": { "texture": "#redpaintedsteelwrench", "uv": [ 6.0, 14.5, 10.0, 15.0 ] }
					}
				},
				{
					"name": "VentVane",
					"from": [ 1.0, 0.0, 0.0 ], 
					"to": [ 5.0, 0.5, 0.5 ], 
					"rotationOrigin": [ 1.0, 0.0, 0.0 ],
					"faces": {
						"north": { "texture": "#redpaintedsteelwrench", "uv": [ 0.0, 0.0, 4.0, 0.5 ], "enabled": false },
						"east": { "texture": "#redpaintedsteelwrench", "uv": [ 0.0, 0.0, 0.5, 0.5 ], "enabled": false },
						"south": { "texture": "#redpaintedsteelwrench", "uv": [ 7.0, 12.5, 11.0, 13.0 ] },
						"west": { "texture": "#redpaintedsteelwrench", "uv": [ 0.0, 0.0, 0.5, 0.5 ], "enabled": false },
						"up": { "texture": "#redpaintedsteelwrench", "uv": [ 6.5, 11.0, 10.5, 11.5 ] },
						"down": { "texture": "#redpaintedsteelwrench", "uv": [ 6.5, 10.5, 10.5, 11.0 ] }
					}
				},
				{
					"name": "VentsideFace",
					"from": [ 5.0, 0.0, 0.0 ], 
					"to": [ 6.0, 6.0, 1.0 ], 
					"rotationOrigin": [ 5.0, 0.0, 0.0 ],
					"faces": {
						"north": { "texture": "#redpaintedsteelwrench", "uv": [ 0.0, 0.0, 1.0, 6.0 ], "enabled": false },
						"east": { "texture": "#redpaintedsteelwrench", "uv": [ 5.0, 2.5, 6.0, 8.5 ] },
						"south": { "texture": "#redpaintedsteelwrench", "uv": [ 5.5, 5.5, 6.5, 11.5 ] },
						"west": { "texture": "#redpaintedsteelwrench", "uv": [ 5.0, 8.5, 6.0, 14.5 ] },
						"up": { "texture": "#redpaintedsteelwrench", "uv": [ 0.0, 0.0, 1.0, 1.0 ], "enabled": false },
						"down": { "texture": "#redpaintedsteelwrench", "uv": [ 0.0, 0.0, 1.0, 1.0 ], "enabled": false }
					}
				},
				{
					"name": "Cube4",
					"from": [ 0.0, 6.0, 0.0 ], 
					"to": [ 6.0, 7.0, 1.0 ], 
					"rotationOrigin": [ 0.0, 6.0, 0.0 ],
					"faces": {
						"north": { "texture": "#redpaintedsteelwrench", "uv": [ 0.0, 0.0, 6.0, 1.0 ], "enabled": false },
						"east": { "texture": "#redpaintedsteelwrench", "uv": [ 3.0, 5.0, 4.0, 6.0 ] },
						"south": { "texture": "#redpaintedsteelwrench", "uv": [ 1.5, 7.5, 7.5, 8.5 ] },
						"west": { "texture": "#redpaintedsteelwrench", "uv": [ 4.0, 8.0, 5.0, 9.0 ] },
						"up": { "texture": "#redpaintedsteelwrench", "uv": [ 0.0, 0.0, 6.0, 1.0 ] },
						"down": { "texture": "#redpaintedsteelwrench", "uv": [ 0.0, 0.0, 6.0, 1.0 ] }
					}
				},
				{
					"name": "Cube2",
					"from": [ 0.0, -1.0, 0.0 ], 
					"to": [ 6.0, 0.0, 1.0 ], 
					"rotationOrigin": [ 0.0, -1.0, 0.0 ],
					"faces": {
						"north": { "texture": "#redpaintedsteelwrench", "uv": [ 0.0, 0.0, 6.0, 1.0 ], "enabled": false },
						"east": { "texture": "#redpaintedsteelwrench", "uv": [ 3.5, 9.0, 4.5, 10.0 ] },
						"south": { "texture": "#redpaintedsteelwrench", "uv": [ 1.0, 11.0, 7.0, 12.0 ] },
						"west": { "texture": "#redpaintedsteelwrench", "uv": [ 7.0, 12.5, 8.0, 13.5 ] },
						"up": { "texture": "#redpaintedsteelwrench", "uv": [ 0.0, 0.0, 6.0, 1.0 ] },
						"down": { "texture": "#redpaintedsteelwrench", "uv": [ 4.0, 12.5, 10.0, 13.5 ] }
					}
				}
			]
		},
		{
			"name": "uppershafthousing",
			"from": [ 1.0, 8.0, 5.0 ], 
			"to": [ 6.0, 14.0, 11.0 ], 
			"rotationOrigin": [ 1.0, 8.0, 5.0 ],
			"faces": {
				"north": { "texture": "#wornsteel", "uv": [ 1.5, 9.5, 6.5, 15.5 ] },
				"east": { "texture": "#wornsteel", "uv": [ 0.0, 10.5, 6.0, 16.5 ], "enabled": false },
				"south": { "texture": "#wornsteel", "uv": [ 1.5, 10.0, 6.5, 16.0 ] },
				"west": { "texture": "#wornsteel", "uv": [ 0.5, 10.0, 6.5, 16.0 ] },
				"up": { "texture": "#wornsteel", "uv": [ 2.0, 4.5, 7.0, 10.5 ] },
				"down": { "texture": "#wornsteel", "uv": [ 0.0, 0.0, 5.0, 6.0 ], "enabled": false }
			},
			"children": [
				{
					"name": "uppershafthousingtrim",
					"from": [ 5.0, 0.0, 0.0 ], 
					"to": [ 6.0, 6.0, 6.0 ], 
					"rotationOrigin": [ 5.0, 0.0, 0.0 ],
					"faces": {
						"north": { "texture": "#redpaintedsteelwrench", "uv": [ 1.5, 10.0, 2.5, 16.0 ] },
						"east": { "texture": "#redpaintedsteelwrench", "uv": [ 0.0, 10.0, 6.0, 16.0 ] },
						"south": { "texture": "#redpaintedsteelwrench", "uv": [ 1.5, 10.0, 2.5, 16.0 ] },
						"west": { "texture": "#redpaintedsteelwrench", "uv": [ 0.5, 11.0, 6.5, 17.0 ], "enabled": false },
						"up": { "texture": "#redpaintedsteelwrench", "uv": [ 2.5, 7.5, 3.5, 13.5 ] },
						"down": { "texture": "#redpaintedsteelwrench", "uv": [ 0.0, 0.0, 1.0, 6.0 ], "enabled": false }
					}
				},
				{
					"name": "MainShaft",
					"from": [ 6.0, 1.5, 1.5 ], 
					"to": [ 7.0, 4.5, 4.5 ], 
					"rotationOrigin": [ 6.0, 3.0, 3.0 ],
					"faces": {
						"north": { "texture": "#redpaintedsteelwrench", "uv": [ 8.0, 1.5, 9.0, 4.5 ] },
						"east": { "texture": "#redpaintedsteelwrench", "uv": [ 7.5, 1.5, 10.5, 4.5 ] },
						"south": { "texture": "#redpaintedsteelwrench", "uv": [ 9.0, 2.0, 10.0, 5.0 ] },
						"west": { "texture": "#redpaintedsteelwrench", "uv": [ 7.5, 1.0, 10.5, 4.0 ], "enabled": false },
						"up": { "texture": "#redpaintedsteelwrench", "uv": [ 8.5, 1.5, 9.5, 4.5 ] },
						"down": { "texture": "#redpaintedsteelwrench", "uv": [ 9.0, 1.0, 10.0, 4.0 ] }
					}
				},
				{
					"name": "MainShaft21",
					"from": [ 7.0, 2.0, 2.0 ], 
					"to": [ 8.0, 4.0, 4.0 ], 
					"rotationOrigin": [ 7.0, 4.0, 3.0 ],
					"faces": {
						"north": { "texture": "#redpaintedsteelwrench", "uv": [ 12.0, 1.5, 13.0, 3.5 ] },
						"east": { "texture": "#redpaintedsteelwrench", "uv": [ 12.0, 1.5, 14.0, 3.5 ] },
						"south": { "texture": "#redpaintedsteelwrench", "uv": [ 12.0, 2.0, 13.0, 4.0 ] },
						"west": { "texture": "#redpaintedsteelwrench", "uv": [ 7.5, 1.0, 9.5, 3.0 ], "enabled": false },
						"up": { "texture": "#redpaintedsteelwrench", "uv": [ 12.0, 1.0, 13.0, 3.0 ] },
						"down": { "texture": "#redpaintedsteelwrench", "uv": [ 12.0, 1.0, 13.0, 3.0 ] }
					}
				}
			]
		},
		{
			"name": "uppershafthousing22",
			"from": [ 16.0, 8.0, 11.0 ], 
			"to": [ 17.0, 14.0, 17.0 ], 
			"rotationOrigin": [ 16.0, 8.0, 11.0 ],
			"rotationY": -180.0,
			"faces": {
				"north": { "texture": "#wornsteel", "uv": [ 1.5, 9.5, 2.5, 15.5 ] },
				"east": { "texture": "#wornsteel", "uv": [ 0.0, 10.5, 6.0, 16.5 ], "enabled": false },
				"south": { "texture": "#wornsteel", "uv": [ 1.5, 10.0, 2.5, 16.0 ] },
				"west": { "texture": "#wornsteel", "uv": [ 0.5, 10.0, 6.5, 16.0 ] },
				"up": { "texture": "#wornsteel", "uv": [ 2.0, 4.5, 3.0, 10.5 ] },
				"down": { "texture": "#wornsteel", "uv": [ 0.0, 0.0, 1.0, 6.0 ] }
			},
			"children": [
				{
					"name": "uppershafthousingtrim23",
					"from": [ 1.0, 0.0, 0.0 ], 
					"to": [ 2.0, 6.0, 6.0 ], 
					"rotationOrigin": [ 1.0, 0.0, 0.0 ],
					"faces": {
						"north": { "texture": "#redpaintedsteelwrench", "uv": [ 1.5, 10.0, 2.5, 16.0 ] },
						"east": { "texture": "#redpaintedsteelwrench", "uv": [ 0.0, 10.0, 6.0, 16.0 ] },
						"south": { "texture": "#redpaintedsteelwrench", "uv": [ 1.5, 10.0, 2.5, 16.0 ] },
						"west": { "texture": "#redpaintedsteelwrench", "uv": [ 0.5, 11.0, 6.5, 17.0 ], "enabled": false },
						"up": { "texture": "#redpaintedsteelwrench", "uv": [ 2.5, 7.5, 3.5, 13.5 ] },
						"down": { "texture": "#redpaintedsteelwrench", "uv": [ 0.0, 0.0, 1.0, 6.0 ] }
					}
				},
				{
					"name": "MainShaft24",
					"from": [ 2.0, 1.5, 1.5 ], 
					"to": [ 3.0, 4.5, 4.5 ], 
					"rotationOrigin": [ 2.0, 3.0, 3.0 ],
					"faces": {
						"north": { "texture": "#redpaintedsteelwrench", "uv": [ 8.0, 1.5, 9.0, 4.5 ] },
						"east": { "texture": "#redpaintedsteelwrench", "uv": [ 7.5, 1.5, 10.5, 4.5 ] },
						"south": { "texture": "#redpaintedsteelwrench", "uv": [ 9.0, 2.0, 10.0, 5.0 ] },
						"west": { "texture": "#redpaintedsteelwrench", "uv": [ 7.5, 1.0, 10.5, 4.0 ], "enabled": false },
						"up": { "texture": "#redpaintedsteelwrench", "uv": [ 8.5, 1.5, 9.5, 4.5 ] },
						"down": { "texture": "#redpaintedsteelwrench", "uv": [ 9.0, 1.0, 10.0, 4.0 ] }
					}
				}
			]
		},
		{
			"name": "SupportRail",
			"from": [ 8.0, 7.0, 6.5 ], 
			"to": [ 16.0, 8.0, 9.5 ], 
			"rotationOrigin": [ 8.0, 7.0, 6.0 ],
			"faces": {
				"north": { "texture": "#wornsteel", "uv": [ 0.0, 0.0, 8.0, 1.0 ] },
				"east": { "texture": "#wornsteel", "uv": [ 0.0, 0.0, 3.0, 1.0 ] },
				"south": { "texture": "#wornsteel", "uv": [ 0.0, 0.0, 8.0, 1.0 ] },
				"west": { "texture": "#wornsteel", "uv": [ 0.0, 0.0, 3.0, 1.0 ] },
				"up": { "texture": "#wornsteel", "uv": [ 0.0, 0.0, 8.0, 3.0 ] },
				"down": { "texture": "#wornsteel", "uv": [ 0.0, 0.0, 8.0, 3.0 ] }
			},
			"children": [
				{
					"name": "SupportRail26",
					"from": [ 0.0, -1.0, 0.5 ], 
					"to": [ 8.0, 0.0, 2.5 ], 
					"rotationOrigin": [ 0.0, -1.0, -0.5 ],
					"faces": {
						"north": { "texture": "#wornsteel", "uv": [ 0.0, 0.0, 8.0, 1.0 ] },
						"east": { "texture": "#wornsteel", "uv": [ 0.0, 0.0, 2.0, 1.0 ] },
						"south": { "texture": "#wornsteel", "uv": [ 0.0, 0.0, 8.0, 1.0 ] },
						"west": { "texture": "#wornsteel", "uv": [ 0.0, 0.0, 2.0, 1.0 ] },
						"up": { "texture": "#wornsteel", "uv": [ 0.0, 0.0, 8.0, 2.0 ] },
						"down": { "texture": "#wornsteel", "uv": [ 0.0, 0.0, 8.0, 2.0 ] }
					}
				},
				{
					"name": "SupportRail27",
					"from": [ 4.0, -7.0, -0.5 ], 
					"to": [ 8.0, -6.0, 3.5 ], 
					"rotationOrigin": [ 4.0, -7.0, -1.5 ],
					"faces": {
						"north": { "texture": "#redpaintedsteelwrench", "uv": [ 12.0, 0.5, 16.0, 1.5 ] },
						"east": { "texture": "#redpaintedsteelwrench", "uv": [ 11.5, 0.0, 15.5, 1.0 ] },
						"south": { "texture": "#redpaintedsteelwrench", "uv": [ 11.5, 1.0, 15.5, 2.0 ] },
						"west": { "texture": "#redpaintedsteelwrench", "uv": [ 12.0, 0.5, 16.0, 1.5 ] },
						"up": { "texture": "#redpaintedsteelwrench", "uv": [ 11.5, 0.5, 15.5, 4.5 ] },
						"down": { "texture": "#redpaintedsteelwrench", "uv": [ 11.5, 1.0, 15.5, 5.0 ] }
					}
				},
				{
					"name": "SupportRail28",
					"from": [ 5.0, -6.0, 0.5 ], 
					"to": [ 7.0, -1.0, 2.5 ], 
					"rotationOrigin": [ 5.0, -6.0, -0.5 ],
					"faces": {
						"north": { "texture": "#bluepaintedwornsteelplate", "uv": [ 0.0, 0.0, 2.0, 5.0 ] },
						"east": { "texture": "#bluepaintedwornsteelplate", "uv": [ 0.0, 0.0, 2.0, 5.0 ] },
						"south": { "texture": "#bluepaintedwornsteelplate", "uv": [ 0.0, 0.0, 2.0, 5.0 ] },
						"west": { "texture": "#bluepaintedwornsteelplate", "uv": [ 0.0, 0.0, 2.0, 5.0 ] },
						"up": { "texture": "#bluepaintedwornsteelplate", "uv": [ 0.0, 0.0, 2.0, 2.0 ] },
						"down": { "texture": "#bluepaintedwornsteelplate", "uv": [ 0.0, 0.0, 2.0, 2.0 ] }
					}
				}
			]
		},
		{
			"name": "BladeJig",
			"from": [ 9.0, 15.0, 7.5 ], 
			"to": [ 17.0, 16.0, 8.5 ], 
			"rotationOrigin": [ 9.0, 15.0, 7.0 ],
			"faces": {
				"north": { "texture": "#wornsteel", "uv": [ 0.0, 0.0, 8.0, 1.0 ] },
				"east": { "texture": "#wornsteel", "uv": [ 0.0, 0.0, 1.0, 1.0 ] },
				"south": { "texture": "#wornsteel", "uv": [ 0.0, 0.0, 8.0, 1.0 ] },
				"west": { "texture": "#wornsteel", "uv": [ 0.0, 0.0, 1.0, 1.0 ] },
				"up": { "texture": "#wornsteel", "uv": [ 0.0, 0.0, 8.0, 1.0 ] },
				"down": { "texture": "#wornsteel", "uv": [ 0.0, 0.0, 8.0, 1.0 ] }
			},
			"children": [
				{
					"name": "Cube1",
					"from": [ 1.0, -1.0, 0.0 ], 
					"to": [ 2.0, 0.0, 1.0 ], 
					"rotationOrigin": [ 1.0, -1.0, 0.0 ],
					"faces": {
						"north": { "texture": "#redpaintedsteelwrench", "uv": [ 0.0, 0.0, 1.0, 1.0 ] },
						"east": { "texture": "#redpaintedsteelwrench", "uv": [ 0.0, 0.0, 1.0, 1.0 ] },
						"south": { "texture": "#redpaintedsteelwrench", "uv": [ 0.0, 0.0, 1.0, 1.0 ] },
						"west": { "texture": "#redpaintedsteelwrench", "uv": [ 0.0, 0.0, 1.0, 1.0 ] },
						"up": { "texture": "#redpaintedsteelwrench", "uv": [ 0.0, 0.0, 1.0, 1.0 ] },
						"down": { "texture": "#redpaintedsteelwrench", "uv": [ 0.0, 0.0, 1.0, 1.0 ] }
					},
					"children": [
						{
							"name": "Cube31",
							"from": [ 0.25, -1.0, 0.25 ], 
							"to": [ 0.5, 0.0, 0.5 ], 
							"rotationOrigin": [ 0.0, -1.0, 0.0 ],
							"faces": {
								"north": { "texture": "#redpaintedsteelwrench", "uv": [ 9.0, 1.0, 9.5, 2.0 ] },
								"east": { "texture": "#redpaintedsteelwrench", "uv": [ 9.0, 1.0, 9.5, 2.0 ] },
								"south": { "texture": "#redpaintedsteelwrench", "uv": [ 8.5, 0.5, 9.0, 1.5 ] },
								"west": { "texture": "#redpaintedsteelwrench", "uv": [ 7.5, 2.0, 8.0, 3.0 ] },
								"up": { "texture": "#redpaintedsteelwrench", "uv": [ 0.0, 0.0, 0.5, 0.5 ], "enabled": false },
								"down": { "texture": "#redpaintedsteelwrench", "uv": [ 14.5, 2.5, 15.0, 3.0 ] }
							}
						}
					]
				},
				{
					"name": "Cube32",
					"from": [ 6.125, -1.0, 0.125 ], 
					"to": [ 6.875, 0.0, 0.875 ], 
					"rotationOrigin": [ 6.0, -1.0, 0.0 ],
					"faces": {
						"north": { "texture": "#redpaintedsteelwrench", "uv": [ 13.5, 2.0, 14.0, 3.0 ] },
						"east": { "texture": "#redpaintedsteelwrench", "uv": [ 12.5, 2.0, 13.0, 3.0 ] },
						"south": { "texture": "#redpaintedsteelwrench", "uv": [ 12.5, 1.5, 13.0, 2.5 ] },
						"west": { "texture": "#redpaintedsteelwrench", "uv": [ 13.0, 2.5, 13.5, 3.5 ] },
						"up": { "texture": "#redpaintedsteelwrench", "uv": [ 0.0, 0.0, 0.5, 0.5 ], "enabled": false },
						"down": { "texture": "#redpaintedsteelwrench", "uv": [ 0.0, 0.0, 0.5, 0.5 ], "enabled": false }
					}
				}
			]
		},
		{
			"name": "wirejunction",
			"from": [ 6.0, 0.0, 0.0 ], 
			"to": [ 10.0, 3.0, 2.0 ], 
			"rotationOrigin": [ 6.0, 0.0, 0.0 ],
			"faces": {
				"north": { "texture": "#redpaintedsteelwrench", "uv": [ 7.0, 0.5, 11.0, 3.5 ] },
				"east": { "texture": "#redpaintedsteelwrench", "uv": [ 7.5, 1.0, 9.5, 4.0 ] },
				"south": { "texture": "#redpaintedsteelwrench", "uv": [ 7.0, 0.0, 11.0, 3.0 ] },
				"west": { "texture": "#redpaintedsteelwrench", "uv": [ 8.5, 0.0, 10.5, 3.0 ] },
				"up": { "texture": "#redpaintedsteelwrench", "uv": [ 7.0, 1.5, 11.0, 3.5 ] },
				"down": { "texture": "#redpaintedsteelwrench", "uv": [ 7.0, 1.0, 11.0, 3.0 ] }
			}
		},
		{
			"name": "wirejunction34",
			"from": [ 6.5, 0.0, 2.0 ], 
			"to": [ 9.5, 2.0, 3.0 ], 
			"rotationOrigin": [ 6.0, 0.0, 2.0 ],
			"faces": {
				"north": { "texture": "#redpaintedsteelwrench", "uv": [ 7.0, 0.5, 10.0, 2.5 ] },
				"east": { "texture": "#redpaintedsteelwrench", "uv": [ 7.5, 1.0, 8.5, 3.0 ] },
				"south": { "texture": "#redpaintedsteelwrench", "uv": [ 7.0, 0.0, 10.0, 2.0 ] },
				"west": { "texture": "#redpaintedsteelwrench", "uv": [ 8.5, 0.0, 9.5, 2.0 ] },
				"up": { "texture": "#redpaintedsteelwrench", "uv": [ 7.0, 1.5, 10.0, 2.5 ] },
				"down": { "texture": "#redpaintedsteelwrench", "uv": [ 7.0, 1.0, 10.0, 2.0 ] }
			}
		},
		{
			"name": "wirejunction35",
			"from": [ 2.5, 0.0, 2.0 ], 
			"to": [ 6.5, 1.0, 3.0 ], 
			"rotationOrigin": [ 2.0, 0.0, 2.0 ],
			"faces": {
				"north": { "texture": "#redpaintedsteelwrench", "uv": [ 7.0, 0.5, 11.0, 1.5 ] },
				"east": { "texture": "#redpaintedsteelwrench", "uv": [ 7.5, 1.0, 8.5, 2.0 ] },
				"south": { "texture": "#redpaintedsteelwrench", "uv": [ 7.0, 0.0, 11.0, 1.0 ] },
				"west": { "texture": "#redpaintedsteelwrench", "uv": [ 8.5, 0.0, 9.5, 1.0 ] },
				"up": { "texture": "#redpaintedsteelwrench", "uv": [ 7.0, 1.5, 11.0, 2.5 ] },
				"down": { "texture": "#redpaintedsteelwrench", "uv": [ 7.0, 1.0, 11.0, 2.0 ] }
			}
		}
	]}